{
  "prayerItems": [
    {
      "title": "Lorem ipsum",
      "date": "2021-11-02",
      "text": "Pellentesque habitant morbi tristique senectus et netus et malesuada fames ac turpis egestas.",
      "completed": true,
      "id": "ea201173-ce7b-4ca6-9866-26351ff0d311"
    },
    {
      "title": "Interdum et malesuada fames ac ante ipsum primis in faucibus",
      "date": "2021-11-09",
      "text": "Mauris massa nisi, scelerisque quis mi at, ornare hendrerit augue. Etiam molestie tellus vel vestibulum pretium.",
      "completed": true,
      "id": "cefa4c5f-acb9-401d-aa1e-1304ccba65f5"
    },
    {
      "title": "Quisque",
      "date": "2021-11-11",
      "text": "Commodo lacus ac sapien venenatis vestibulum. Pellentesque egestas ex nec purus dapibus sagittis.",
      "completed": false,
      "id": "a2acc6b7-d220-44e7-a499-5ccad42f5eb1"
    },
    {
      "title": "Phasellus sit amet sagittis turpis",
      "date": "2021-11-21",
      "text": "Etiam id mauris eu lectus fringilla imperdiet.",
      "completed": true,
      "id": "e6a5c54b-f6d6-444e-94ed-89b70f6f382d"
    },
    {
      "title": "Integer luctus enim ac neque semper, non porta lorem finibus",
      "date": "2021-11-23",
      "text": "Cras id justo a metus semper congue nec quis lorem. Mauris eleifend placerat felis, a finibus dui efficitur eget.",
      "completed": false,
      "id": "85fff502-0f65-465a-8646-8ed90c792b2a"
    }
  ],
  "users": [
    {
      "firstName": "David",
      "lastName": "Hunter",
      "displayName": "Hunter",
      "signupDate": "2021-11-01",
      "id": "2f740108-8596-4a8a-b334-518ab34a8c50",
      "isAdmin": true,
      "settings": {
        "showSizeIndicator": false,
        "showToastTester": false,
        "actions": {
          "showSettings": true,
          "showPrayerEntry": true
        },
        "home": {
          "showSettings": true,
          "showActions": true,
          "showPrayers": true,
          "statsFilter": "alltime",
          "vizualizationsOrder": [
            { "name": "AllActivities", "active": true, "order": 0 },
            { "name": "OldVsNew", "active": false, "order": 1 },
            { "name": "ReadScripture", "active": true, "order": 2 },
            { "name": "DetailedReading", "active": true, "order": 3 }
          ]
        },
        "prayer": {
          "showSettings": true,
          "showAllItems": true,
          "sort": "date-asc",
          "filters": {
            "showAll": true,
            "showUnLabeled": true,
            "showRequests": true,
            "showPraise": true,
            "showConfessions": true
          }
        },
        "read": {
          "showSettings": true,
          "defaultVersion": "ESV",
          "showReadingPlan": true
        }
      }
    }
  ],
  "actions": {
    "custom": [
      {
        "id": "186012ac-1978-442c-8c93-78b1f4c3e47b",
        "displayName": "Discipled my kids"
      },
      {
        "id": "dfd2065a-7e64-4c4c-8b23-55b98dafed9f",
        "displayName": "Prepared music for the service"
      },
      {
        "id": "4f995e2e-b6a8-49a2-8835-f3177509cc08",
        "displayName": "Led a bible study"
      }
    ]
  },
  "passages": [
    {
      "osis": "Matt.5.5",
      "version": "ESV",
      "id": "3593f37f-2160-4600-8006-8f5f395b3ce5",
      "date": "2021-12-20"
    },
    {
      "osis": "Rev.12.1",
      "version": "ESV",
      "id": "104aa616-8aad-4796-bab0-9ce24d5e8382",
      "date": "2021-12-20"
    }
  ]
}
